example_package/__init__.py
example_package/main.py
example_package/print.py
yeannhua_example_package_demo-0.2.0.dist-info/METADATA
yeannhua_example_package_demo-0.2.0.dist-info/WHEEL
yeannhua_example_package_demo-0.2.0.dist-info/licenses/LICENSE
yeannhua_example_package_demo-0.2.0.dist-info/RECORD
